{
  "generator-jhipster": {
    "applicationType": "monolith",
    "gitCompany": "",
    "baseName": "medikal",
    "packageName": "io.github.jhipster.application",
    "packageFolder": "io/github/jhipster/application",
    "serverPort": 8080,
    "serviceDiscoveryType": false,
    "authenticationType": "jwt",
    "uaaBaseName": "../uaa",
    "cacheProvider": "ehcache",
    "enableHibernateCache": true,
    "websocket": false,
    "databaseType": "sql",
    "devDatabaseType": "h2Disk",
    "prodDatabaseType": "mysql",
    "searchEngine": "elasticsearch",
    "enableSwaggerCodegen": false,
    "messageBroker": false,
    "buildTool": "maven",
    "useSass": true,
    "clientPackageManager": "npm",
    "testFrameworks": [
      "gatling"
    ],
    "enableTranslation": true,
    "nativeLanguage": "en",
    "languages": [
      "ro",
      "en"
    ],
    "clientFramework": "angularX",
    "jhiPrefix": "jhi",
    "jhipsterVersion": "6.1.2",
    "jwtSecretKey": "YWUzZDRlOWM5NDM3ZmQ3YjE2ODI4NTg3ZGExMDFjZWI5ZjkyYmE1OTdhOTFjMzQwYjMwZTA1NzJjZGJiYjVjYWE3OTE5YzBkNGFkMDhkOTIyZDAzMDc2YWZhZDcyM2I1YTljNjFkNmVjMWUwODE3YWE1YjNmODg3YmE3NGI3Zjk=",
    "clientTheme": "none",
    "entitySuffix": "",
    "dtoSuffix": "DTO",
    "otherModules": []
  },
  "git-provider": "GitHub",
  "git-company": "sebastianmlr",
  "repository-name": "medikal"
}